gabia_sms/__init__.py
gabia_sms/codes.py
gabia_sms/core.py
gabia_sms/exceptions.py
gabia_sms/formats.py
gabia_sms/parser.py
gabia_sms/shortcuts.py
gabia_sms/utils.py
gabia_sms_python-1.0.4.dist-info/METADATA
gabia_sms_python-1.0.4.dist-info/WHEEL
gabia_sms_python-1.0.4.dist-info/top_level.txt
gabia_sms_python-1.0.4.dist-info/RECORD
