Metadata-Version: 2.1
Name: gabia-sms-python
Version: 1.0.4
Summary: Send SMS messages to mobile devices through GABIA SMS api.
Home-page: https://github.com/taylor-kang/gabia-sms-python.git
Author: Taehee Kang
Author-email: taehee.taylor.kang@gmail.com
License: UNKNOWN
Download-URL: https://github.com/taylor-kang/gabia-sms-python/archive/master.zip
Platform: UNKNOWN
Classifier: Intended Audience :: Developers
Classifier: Operating System :: OS Independent
Classifier: Programming Language :: Python
Classifier: Programming Language :: Python :: 2
Classifier: Programming Language :: Python :: 2.7
Classifier: Programming Language :: Python :: 3
Classifier: Programming Language :: Python :: 3.4
Classifier: Programming Language :: Python :: 3.5
Classifier: Programming Language :: Python :: 3.7
